{"संगीत":[{"question":"माली का सबसे प्रतीकात्मक पारंपरिक वाद्ययंत्र कौन सा है?","answers":{"कोरा":true,"बालाफोन":false,"डीजेम्बे":false,"एनगोनी":false},"id":"music_0000","correctAnswer":"कोरा","explanation":"कोरा, एक 21-तार वाली वीणा-वीणा, माली का सबसे प्रतीकात्मक पारंपरिक वाद्ययंत्र है।"},{"question":"मालियन 'ब्लूज़ का राजा' किसे माना जाता है?","answers":{"अली फ़र्का तूरे":true,"सलीफ़ कीता":false,"ओउमौ संगारे":false,"अमादौ और मरियम":false},"id":"music_0001","correctAnswer":"अली फ़र्का तूरे","explanation":"डेजर्ट ब्लूज़ से प्रेरित अपनी गिटार शैली के लिए अली फ़र्का टूरे को मालियन 'किंग ऑफ़ ब्लूज़' उपनाम दिया गया है।"},{"question":"लोकतांत्रिक गणराज्य कांगो में किस संगीत शैली की उत्पत्ति हुई?","answers":{"कांगोलेस रूंबा":true,"उच्च जीवन":false,"अफ्रोबीट":false,"कूपे-डेकाले":false},"id":"music_0002","correctAnswer":"कांगोलेस रूंबा","explanation":"कांगोलेस रूंबा एक संगीत शैली है जो कांगो लोकतांत्रिक गणराज्य में पैदा हुई है, जिसमें अफ्रीकी लय और क्यूबा के प्रभाव का मिश्रण है।"},{"question":"अफ्रोबीट को दुनिया भर में किसने लोकप्रिय बनाया?","answers":{"फेला कुटी (नाइजीरिया)":true,"मनु डिबांगो (कैमरून)":false,"युसू एन'डौर (सेनेगल)":false,"एंजेलिक किडजो (बेनिन)":false},"id":"music_0003","correctAnswer":"फेला कुटी (नाइजीरिया)","explanation":"नाइजीरियाई संगीतकार फेला कुटी ने 1970 के दशक में अफ्रोबीट को बनाया और लोकप्रिय बनाया।"},{"question":"मोरक्कन गनावा संगीत में पारंपरिक रूप से कौन सा वाद्ययंत्र प्रयोग किया जाता है?","answers":{"गुएम्ब्री":true,"ऊद":false,"क़ानून":false,"नी":false},"id":"music_0004","correctAnswer":"गुएम्ब्री","explanation":"गुएम्ब्री, एक तीन-तार वाला ल्यूट, मोरक्कन गनावा संगीत का प्रतीक पारंपरिक वाद्ययंत्र है।"},{"question":"'अफ्रीका की दिवा' उपनाम किसे दिया जाता है?","answers":{"मिरियम मेकबा (दक्षिण अफ्रीका)":true,"एंजेलिक किडजो (बेनिन)":false,"सेसरिया इवोरा (केप वर्डे)":false,"ओउमौ संगारे (माली)":false},"id":"music_0005","correctAnswer":"मिरियम मेकबा (दक्षिण अफ्रीका)","explanation":"दक्षिण अफ्रीकी गायिका मिरियम मेकबा को उनके संगीत प्रभाव और प्रतिबद्धता के लिए 'अफ्रीका की दिवा' उपनाम दिया गया है।"},{"question":"1960 के दशक में जमैका में किस संगीत शैली की शुरुआत हुई?","answers":{"रेग":true,"स्का":false,"द रॉकस्टेडी":false,"डब":false},"id":"music_0006","correctAnswer":"रेग","explanation":"रेगे का जन्म 1960 के दशक में जमैका में हुआ था, विशेषकर बॉब मार्ले द्वारा।"},{"question":"'द गोल्डन वॉइस' उपनाम वाला मालियन गायक कौन है?","answers":{"सलीफ़ कीता":true,"अली फ़र्का तूरे":false,"टौमानी डायबेटे":false,"रोकिया ट्रोरे":false},"id":"music_0007","correctAnswer":"सलीफ़ कीता","explanation":"सलीफ़ कीटा को उनकी गायकी की ताकत के लिए 'अफ्रीका की गोल्डन वॉयस' का उपनाम दिया गया है।"},{"question":"किस तालवाद्य की उत्पत्ति पश्चिम अफ़्रीका में हुई?","answers":{"डीजेम्बे":true,"बोंगो":false,"कोंगस":false,"बैटरी":false},"id":"music_0008","correctAnswer":"डीजेम्बे","explanation":"डीजेम्बे, एक प्याली के आकार का ड्रम, पश्चिम अफ्रीका से उत्पन्न एक ताल वाद्य यंत्र है।"},{"question":"'लंबाडा' की रचना किसने की?","answers":{"काओमा (फ्रेंको-ब्राज़ीलियाई समूह)":true,"कार्लोस सैन्टाना":false,"जिप्सी किंग्स":false,"रिकी मार्टिन":false},"id":"music_0009","correctAnswer":"काओमा (फ्रेंको-ब्राज़ीलियाई समूह)","explanation":"'लाम्बाडा' गीत को 1989 में फ्रेंको-ब्राज़ीलियाई समूह काओमा द्वारा लोकप्रिय बनाया गया था।"},{"question":"माली के राष्ट्रीय ऑर्केस्ट्रा का क्या नाम है?","answers":{"माली का राष्ट्रीय ऑर्केस्ट्रा 'ए'":true,"माली सिम्फनी ऑर्केस्ट्रा":false,"माली गणराज्य का ऑर्केस्ट्रा":false,"मालियन नेशनल ऑर्केस्ट्रा":false},"id":"music_0010","correctAnswer":"माली का राष्ट्रीय ऑर्केस्ट्रा 'ए'","explanation":"माली का राष्ट्रीय ऑर्केस्ट्रा 'ए' स्वतंत्रता के बाद मालियन संगीत परिदृश्य पर प्रमुख समूहों में से एक था।"},{"question":"जैज़ का जनक किसे माना जाता है?","answers":{"लुई आर्मस्ट्रांग":true,"ड्यूक एलिंगटन":false,"चार्ली पार्कर":false,"माइल्स डेविस":false},"id":"music_0011","correctAnswer":"लुई आर्मस्ट्रांग","explanation":"शैली के विकास में अग्रणी भूमिका के लिए लुई आर्मस्ट्रांग को अक्सर जैज़ का जनक माना जाता है।"},{"question":"न्यू ऑरलियन्स में किस संगीत शैली की उत्पत्ति हुई?","answers":{"जाज":true,"ब्लूज़":false,"इंजील":false,"ताल और ब्लूज़":false},"id":"music_0012","correctAnswer":"जाज","explanation":"जैज़ की उत्पत्ति 19वीं सदी के अंत और 20वीं सदी की शुरुआत में न्यू ऑरलियन्स में हुई थी।"},{"question":"मंडिंका संगीत को दुनिया भर में किसने लोकप्रिय बनाया?","answers":{"टौमानी डायबेटे":true,"अली फ़र्का तूरे":false,"सलीफ़ कीता":false,"रोकिया ट्रोरे":false},"id":"music_0013","correctAnswer":"टौमानी डायबेटे","explanation":"तूमानी डायबेटे, कोरा गुणी, ने मंडिंका संगीत को दुनिया भर में प्रसिद्ध बनाने में बड़े पैमाने पर योगदान दिया है।"},{"question":"कौन सा पारंपरिक उपकरण गुंजयमान यंत्र के रूप में कैलाबैश का उपयोग करता है?","answers":{"बालाफोन":true,"कोरा":false,"एनगोनी":false,"डीजेम्बे":false},"id":"music_0014","correctAnswer":"बालाफोन","explanation":"बालाफ़ोन, एक पारंपरिक पश्चिम अफ़्रीकी ज़ाइलोफोन, अपने लकड़ी के ब्लेड के नीचे अनुनादक के रूप में लौकी का उपयोग करता है।"},{"question":"'द ग्रिओट ऑफ़ द ब्लूज़' उपनाम किसे दिया जाता है?","answers":{"अली फ़र्का तूरे":true,"सलीफ़ कीता":false,"टौमानी डायबेटे":false,"बाउबकर ट्रोरे":false},"id":"music_0015","correctAnswer":"अली फ़र्का तूरे","explanation":"मालियन परंपरा और ब्लूज़ को मिश्रित करने वाली अपनी शैली के लिए अली फ़र्का टूरे को 'द ग्रिओट ऑफ़ द ब्लूज़' का उपनाम भी दिया गया है।"},{"question":"कौन सी संगीत शैली मूल रूप से केप वर्डे की है?","answers":{"सुबह":true,"फ़नाना":false,"बटुक":false,"कोलाडेरा":false},"id":"music_0016","correctAnswer":"सुबह","explanation":"मोर्ना, सेसरिया इवोरा द्वारा पहनी जाने वाली एक उदास संगीत शैली, केप वर्डे से उत्पन्न हुई है।"},{"question":"2010 विश्व कप के लिए 'वाका वाका (इस बार अफ्रीका के लिए)' की रचना किसने की?","answers":{"शकीरा":true,"जेनिफर लोपेज":false,"बेयोंस":false,"रिहाना":false},"id":"music_0017","correctAnswer":"शकीरा","explanation":"शकीरा ने दक्षिण अफ्रीका में 2010 विश्व कप का आधिकारिक गान 'वाका वाका (इस बार अफ्रीका के लिए)' प्रस्तुत किया।"},{"question":"गनावा संगीत का पारंपरिक वाद्ययंत्र कौन सा है?","answers":{"गुएम्ब्री (3-स्ट्रिंग ल्यूट)":true,"ऊद":false,"कोरा":false,"एनगोनी":false},"id":"music_0018","correctAnswer":"गुएम्ब्री (3-स्ट्रिंग ल्यूट)","explanation":"गुएम्ब्री, एक तीन-तार वाला ल्यूट-ड्रम, मोरक्कन गनावा संगीत का केंद्रीय वाद्ययंत्र है।"},{"question":"सेनेगल एमबालैक्स का राजा किसे माना जाता है?","answers":{"यूसू एन'डौर":true,"बाबा माल":false,"इस्माइल लो":false,"ऑर्केस्ट्रा बाओबाब":false},"id":"music_0019","correctAnswer":"यूसू एन'डौर","explanation":"यूसू एन'डॉर को सेनेगल की एक लोकप्रिय संगीत शैली एमबालैक्स का राजा माना जाता है।"},{"question":"ब्राज़ील में किस संगीत शैली का जन्म हुआ?","answers":{"बोसा नोवा":true,"सांबा":false,"फ़ोरो":false,"लम्बाडा":false},"id":"music_0020","correctAnswer":"बोसा नोवा","explanation":"बोसा नोवा, सांबा और जैज़ का मिश्रण, 1950 के दशक में ब्राज़ील में जन्मी एक संगीत शैली है।"},{"question":"माली में वासोलौ संगीत को किसने लोकप्रिय बनाया?","answers":{"ओउमौ संगारे":true,"सलीफ़ कीता":false,"अली फ़र्का तूरे":false,"रोकिया ट्रोरे":false},"id":"music_0021","correctAnswer":"ओउमौ संगारे","explanation":"ओउमौ संगारे ने दक्षिणी माली से उत्पन्न वासोलौ संगीत को व्यापक रूप से लोकप्रिय बनाया।"},{"question":"किस पारंपरिक मालियन वाद्ययंत्र में 21 तार होते हैं?","answers":{"कोरा":true,"एनगोनी":false,"बालाफोन":false,"गुएम्ब्री":false},"id":"music_0022","correctAnswer":"कोरा","explanation":"कोरा 21 तारों वाला एक पारंपरिक मालियन वाद्ययंत्र है, जिसे पश्चिम अफ़्रीकी ग्रिओट्स द्वारा बजाया जाता है।"},{"question":"'द क्वीन ऑफ एफ्रो-पॉप' उपनाम किसे दिया जाता है?","answers":{"एंजेलिक किडजो":true,"मरियम मेकबा":false,"सेसरिया इवोरा":false,"ओउमौ संगारे":false},"id":"music_0023","correctAnswer":"एंजेलिक किडजो","explanation":"बेनिनीज़ गायिका एंजेलिक किडजो को उनके अंतर्राष्ट्रीय प्रभाव के लिए 'अफ्रो-पॉप की रानी' उपनाम दिया गया है।"},{"question":"क्यूबा में किस संगीत शैली की उत्पत्ति हुई?","answers":{"साल्सा":true,"चा-चा-चा":false,"मम्बो":false,"ध्वनि":false},"id":"music_0024","correctAnswer":"साल्सा","explanation":"साल्सा, अफ़्रीकी-क्यूबा लय का मिश्रण, क्यूबा से उत्पन्न एक संगीत शैली है।"},{"question":"'अफ्रीका' की रचना किसने की?","answers":{"सलीफ़ कीता":true,"अली फ़र्का तूरे":false,"टौमानी डायबेटे":false,"ओउमौ संगारे":false},"id":"music_0025","correctAnswer":"सलीफ़ कीता","explanation":"'अफ़्रीका' गीत की रचना और प्रस्तुति मालियन गायक सलीफ़ कीता ने की थी।"},{"question":"कौन सा पारंपरिक वाद्य यंत्र तनी हुई जानवरों की खाल का उपयोग करता है?","answers":{"डीजेम्बे":true,"बालाफोन":false,"कोरा":false,"एनगोनी":false},"id":"music_0026","correctAnswer":"डीजेम्बे","explanation":"डीजेम्बे, एक अफ़्रीकी ड्रम, अपनी ध्वनि उत्पन्न करने के लिए लकड़ी के बक्से पर खींची गई जानवरों की खाल का उपयोग करता है।"},{"question":"घाना की उच्च जीवन शैली का जनक किसे माना जाता है?","answers":{"मेन्साह":true,"अमाके देदे":false,"कोजो अंत्वी":false,"Sarkodie":false},"id":"music_0027","correctAnswer":"मेन्साह","explanation":"ई.टी. मेन्सा को घाना में जन्मी संगीत शैली हाईलाइफ का जनक माना जाता है।"},{"question":"डोमिनिकन गणराज्य में किस संगीत शैली का जन्म हुआ?","answers":{"बचाता":true,"मेरेंग्यू":false,"साल्सा":false,"रेगेटन":false},"id":"music_0028","correctAnswer":"बचाता","explanation":"बाचाटा डोमिनिकन गणराज्य में जन्मी एक रोमांटिक संगीत शैली है।"},{"question":"तुआरेग संगीत (डेजर्ट ब्लूज़) को किसने लोकप्रिय बनाया?","answers":{"तिनारीवेन":true,"बॉम्बिनो":false,"टैमिक्रेस्ट":false,"टेराकाफ्ट":false},"id":"music_0029","correctAnswer":"तिनारीवेन","explanation":"टिनारिवेन समूह ने तुआरेग संगीत, जिसे 'डेजर्ट ब्लूज़' भी कहा जाता है, को दुनिया भर में लोकप्रिय बनाने में बड़े पैमाने पर योगदान दिया।"},{"id":"music_0030","question":"How many strings does a standard classical guitar have?","options":["6","4","8","12"],"correctAnswer":"6","explanation":"A classical guitar has six strings.","difficulty":"easy"},{"id":"music_0031","question":"What is Salif Keïta mainly known for?","options":["Singing","Drums","Saxophone","Violin"],"correctAnswer":"Singing","explanation":"Salif Keïta is mainly known as a singer.","difficulty":"easy"},{"id":"music_0032","question":"Which note follows “C” (do) in a major scale?","options":["D (re)","E (mi)","F (fa)","G (sol)"],"correctAnswer":"D (re)","explanation":"C, D, E, F, G, A, B.","difficulty":"easy"},{"id":"music_0033","question":"बॉब मार्ले ने किस जमैका संगीत शैली को लोकप्रिय बनाया?","options":["रेग","केलिप्सो","साल्सा","ज़ौक"],"correctAnswer":"रेग","explanation":"बॉब मार्ले ने जमैका के रेगे को दुनिया भर में मशहूर किया।","difficulty":"easy"},{"id":"music_0034","question":"How many movements does a typical classical symphony have?","options":["4","2","6","1"],"correctAnswer":"4","explanation":"A classical symphony often has four movements.","difficulty":"medium"},{"id":"music_0035","question":"Which Malian artist is linked to the album “Moffou”?","options":["Salif Keïta","Ali Farka Touré","Oumou Sangaré","Amadou & Mariam"],"correctAnswer":"Salif Keïta","explanation":"Moffou (2002) is by Salif Keïta.","difficulty":"hard"},{"id":"music_0036","question":"Which symbol indicates silence in music?","options":["A rest","A sharp","A flat","The treble clef"],"correctAnswer":"A rest","explanation":"Rests indicate pauses/silence.","difficulty":"medium"},{"id":"music_0037","question":"Which string instrument is played with a bow?","options":["Violin","Guitar","Harp","Ukulele"],"correctAnswer":"Violin","explanation":"The violin is played with a bow.","difficulty":"easy"},{"id":"music_0038","question":"Which Malian festival celebrates desert music?","options":["Festival in the Desert","Glastonbury","Coachella","Jazz in Marciac"],"correctAnswer":"Festival in the Desert","explanation":"The Festival in the Desert was held near Timbuktu.","difficulty":"medium"},{"id":"music_0039","question":"Which clef is most common for beginner piano?","options":["Treble clef","C clef","Bass clef only","Percussion clef"],"correctAnswer":"Treble clef","explanation":"The treble clef is taught first most often.","difficulty":"easy"}]}
